{
  "overall_score": 0.63,
  "eval_seeds": {
    "easy": [
      42,
      43,
      44
    ],
    "medium": [
      7,
      8,
      9
    ],
    "hard": [
      13,
      14,
      15
    ]
  },
  "difficulties": [
    {
      "difficulty": "easy",
      "score": 0.989,
      "total_reward": 111.0,
      "episodes": [
        {
          "episode": 1,
          "seed": 42,
          "score": 0.99,
          "total_reward": 34.0
        },
        {
          "episode": 2,
          "seed": 43,
          "score": 0.99,
          "total_reward": 40.0
        },
        {
          "episode": 3,
          "seed": 44,
          "score": 0.99,
          "total_reward": 37.0
        }
      ]
    },
    {
      "difficulty": "medium",
      "score": 0.875,
      "total_reward": 125.0,
      "episodes": [
        {
          "episode": 1,
          "seed": 7,
          "score": 0.875,
          "total_reward": 41.0
        },
        {
          "episode": 2,
          "seed": 8,
          "score": 0.875,
          "total_reward": 45.0
        },
        {
          "episode": 3,
          "seed": 9,
          "score": 0.875,
          "total_reward": 39.0
        }
      ]
    },
    {
      "difficulty": "hard",
      "score": 0.431,
      "total_reward": 95.0,
      "episodes": [
        {
          "episode": 1,
          "seed": 13,
          "score": 0.606,
          "total_reward": 62.0
        },
        {
          "episode": 2,
          "seed": 14,
          "score": 0.369,
          "total_reward": 24.0
        },
        {
          "episode": 3,
          "seed": 15,
          "score": 0.32,
          "total_reward": 9.0
        }
      ]
    }
  ]
}